postman_api/__init__.py
postman_api/main.py
postman_api/schemas.py
sideko_postman_api-1.0.0.dist-info/METADATA
sideko_postman_api-1.0.0.dist-info/WHEEL
sideko_postman_api-1.0.0.dist-info/RECORD
